adamapi/__init__.py
adamapi/authorization.py
adamapi/datasets.py
adamapi/get_data.py
adamapi/search.py
adamapi-2.2.2.3.dist-info/LICENSE
adamapi-2.2.2.3.dist-info/METADATA
adamapi-2.2.2.3.dist-info/WHEEL
adamapi-2.2.2.3.dist-info/top_level.txt
adamapi-2.2.2.3.dist-info/RECORD
