Metadata-Version: 2.1
Name: adamapi
Version: 2.2.2.3
Summary: Python Adam API
Home-page: https://git.services.meeo.it/das/adamapi
Author: MEEO s.r.l.
Author-email: info@meeo.it
Classifier: Programming Language :: Python :: 3
Classifier: License :: OSI Approved :: MIT License
Classifier: Operating System :: Unix
Requires-Python: >=3.10
License-File: LICENSE
Requires-Dist: requests==2.32.3
Requires-Dist: tqdm==4.66.5
